discord/ext/ipc/__init__.py
discord/ext/ipc/client.py
discord/ext/ipc/errors.py
discord/ext/ipc/objects.py
discord/ext/ipc/server.py
better_ipc-2.0.3.dist-info/LICENSE
better_ipc-2.0.3.dist-info/METADATA
better_ipc-2.0.3.dist-info/WHEEL
better_ipc-2.0.3.dist-info/top_level.txt
better_ipc-2.0.3.dist-info/RECORD
